{"cameraMode":{"drawMode":0,"name":"Shaded","section":"Shading Mode"},"sceneLighting":false,"audioPlay":false,"sceneViewState":{"m_AlwaysRefresh":false,"showFog":true,"showSkybox":false,"showFlares":true,"showImageEffects":true,"showParticleSystems":true,"showVisualEffectGraphs":true,"m_FxEnabled":true},"in2DMode":false,"pivot":{"x":-3.832979917526245,"y":2.4999191761016847,"z":0.07913151383399964},"rotation":{"x":0.06684012711048126,"y":0.7813204526901245,"z":-0.08495817333459854,"w":0.6147111058235169},"size":0.4440838694572449,"orthographic":false}